{
"nodes":
[{"name": "山东高速路桥集团股份有限公司", "value": 26813289800.0, "category": 803}, {"name": "山东高速股份有限公司", "value": 243100.11, "category": 803}, {"name": "威海市商业银行股份有限公司", "value": 201.16, "category": 803}, {"name": "山东高速集团有限公司", "value": 0, "category": 803}, {"name": "山东高速集团河南许禹公路有限公司", "value": 60.0, "category": 803}, {"name": "山东高速集团四川乐宜公路有限公司", "value": 1444.38, "category": 803}, {"name": "山东高速集团河南许亳公路有限公司", "value": 675.38, "category": 803}, {"name": "山东高速置业发展有限公司", "value": 2659.16, "category": 803}, {"name": "山东高速实业发展有限公司", "value": 139.0, "category": 803}, {"name": "山东高速信息工程有限公司", "value": 47.23, "category": 803}, {"name": "山东高速潍莱公路有限公司", "value": 976.18, "category": 803}, {"name": "山东高速公路运营管理有限公司", "value": 3535.61, "category": 803}, {"name": "山东高速服务区管理有限公司", "value": 82.07, "category": 803}, {"name": "山东高速投资控股有限公司", "value": 11.2, "category": 803}, {"name": "锡林浩特鲁地矿业有限公司", "value": 308.8, "category": 803}, {"name": "山东高速四川产业发展有限公司", "value": 0, "category": 803}, {"name": "山东高速青岛发展有限公司", "value": 700.0, "category": 803}, {"name": "山东高速物资集团总公司", "value": 32884.36, "category": 803}, {"name": "山东高速交通物流投资有限公司", "value": 3010.37, "category": 803}, {"name": "山东利津黄河公路大桥有限公司", "value": 190.48, "category": 803}, {"name": "云南锁蒙高速公路有限公司", "value": 23755.06, "category": 803}, {"name": "山东高速物资储运有限公司", "value": 2643.53, "category": 803}, {"name": "莱州市北莱公路投资有限公司", "value": 958.62, "category": 803}, {"name": "山东省高速公路建设材料有限公司", "value": 46667.96, "category": 803}, {"name": "内蒙古鲁桥置业有限公司", "value": 173.04, "category": 803}, {"name": "山东农村经济开发投资公司", "value": 370.45, "category": 803}, {"name": "高速集团四川乐自公路有限公司", "value": 22640.1, "category": 803}, {"name": "山东高速齐鲁建设集团公司", "value": 348.12, "category": 803}, {"name": "山东高速青岛胶州湾大桥投资发展有限公司", "value": 498.29, "category": 803}, {"name": "山东高速青岛公路有限公司", "value": 4994.06, "category": 803}, {"name": "湖南衡邵高速公路有限公司", "value": 1819.11, "category": 803}, {"name": "山东高速云南发展有限公司", "value": 3269.38, "category": 803}, {"name": "山东高速工程检测有限公司", "value": 78.61, "category": 803}, {"name": "山东高速红河交通投资有限公司", "value": 358.43, "category": 803}, {"name": "鲁南高速铁路有限公司", "value": 20285.22, "category": 803}, {"name": "昆明新机场高速公路建设发展有限公司", "value": 591.54, "category": 803}, {"name": "山东高速高广公路有限公司", "value": 37669.29, "category": 803}, {"name": "山东葛洲坝济泰高速公路有限公司", "value": 30749.46, "category": 803}, {"name": "山东葛洲坝巨单高速公路有限公司", "value": 17337.6, "category": 803}, {"name": "湖北武荆高速公路发展有限公司", "value": 9115.41, "category": 803}, {"name": "山东高速公路发展有限公司", "value": 2195.94, "category": 803}, {"name": "宝兴国晟矿业有限公司", "value": 21.86, "category": 803}, {"name": "山东高速湖北发展有限公司", "value": 0, "category": 803}, {"name": "山东鄄菏高速公路有限公司", "value": 627.06, "category": 803}, {"name": "山东高速齐鲁建设集团建筑工程有限公司", "value": 885.77, "category": 803}, {"name": "山东高速路用新材料技术有限公司", "value": 1404.5, "category": 803}, {"name": "山东大莱龙铁路有限责任公司", "value": 58.8, "category": 803}, {"name": "德州国力化工科技有限公司", "value": 42.12, "category": 803}, {"name": "山东高速泰东公路有限公司", "value": 137185.66, "category": 803}, {"name": "山东高速青岛物流发展有限公司", "value": 5346.28, "category": 803}, {"name": "山东高速临枣至枣木公路有限公司", "value": 29922.93, "category": 803}, {"name": "山东高速龙青公路有限公司", "value": 117574.18, "category": 803}, {"name": "山东高速济泰城际公路有限公司", "value": 382.89, "category": 803}, {"name": "山东高速海南发展有限公司", "value": 1452.68, "category": 803}, {"name": "山东高速潍日公路有限公司", "value": 96341.96, "category": 803}, {"name": "山东鸿林工程技术有限公司", "value": 51.02, "category": 803}, {"name": "山东高速蓬莱发展有限公司", "value": 7546.34, "category": 803}, {"name": "山东高速绿城置业投资有限公司", "value": 420.66, "category": 803}, {"name": "山东葛洲坝枣菏高速公路有限公司", "value": 58666.82, "category": 803}, {"name": "青岛众钧泰置业有限公司", "value": 165.0, "category": 803}, {"name": "山东省三益工程建设监理有限公司", "value": 0.08, "category": 803}, {"name": "山东高速赛邦能源科技有限公司", "value": 1.38, "category": 803}, {"name": "山东高速国际旅游有限公司", "value": 116.95, "category": 803}, {"name": "山东高速四川投资开发有限公司", "value": 1434.44, "category": 803}, {"name": "滕州新奥能源物流港有限公司", "value": 4368.13, "category": 803}, {"name": "山东铁路发展基金有限公司,山东铁路投资控股集团有限公司", "value": 0, "category": 803}, {"name": "济宁市鸿翔公路勘察设计研究院有限公司", "value": 193.58, "category": 803}, {"name": "青岛众昌泰置业有限公司", "value": 185.0, "category": 803}, {"name": "山东高速章丘置业发展有限公司", "value": 49.51, "category": 803}, {"name": "山东高速集团有限公司及其下属子公司", "value": 623100.0, "category": 803}, {"name": "山东高速集团有限公司,山东高速股份集团有限公司,青岛冠中生态股份有限公司,光合新兴产业控股集团股份有限公司", "value": 2000.0, "category": 803}],
"links":
[{"source": "山东高速路桥集团股份有限公司", "target": "山东高速股份有限公司", "value": 1.0289141418983104e-05}, {"source": "山东高速路桥集团股份有限公司", "target": "威海市商业银行股份有限公司", "value": 8.514038466879515e-09}, {"source": "山东高速路桥集团股份有限公司", "target": "山东高速集团有限公司", "value": 0.0}, {"source": "山东高速路桥集团股份有限公司", "target": "山东高速集团河南许禹公路有限公司", "value": 2.539482541324174e-09}, {"source": "山东高速路桥集团股份有限公司", "target": "山东高速集团四川乐宜公路有限公司", "value": 6.113296321729685e-08}, {"source": "山东高速路桥集团股份有限公司", "target": "山东高速集团河南许亳公路有限公司", "value": 2.8585261979325344e-08}, {"source": "山东高速路桥集团股份有限公司", "target": "山东高速置业发展有限公司", "value": 1.125481732431265e-07}, {"source": "山东高速路桥集团股份有限公司", "target": "山东高速实业发展有限公司", "value": 5.88313455406767e-09}, {"source": "山东高速路桥集团股份有限公司", "target": "山东高速信息工程有限公司", "value": 1.9989960071123456e-09}, {"source": "山东高速路桥集团股份有限公司", "target": "山东高速潍莱公路有限公司", "value": 4.1316534453163867e-08}, {"source": "山东高速路桥集团股份有限公司", "target": "山东高速公路运营管理有限公司", "value": 1.496436644655194e-07}, {"source": "山东高速路桥集团股份有限公司", "target": "山东高速服务区管理有限公司", "value": 3.473588869441249e-09}, {"source": "山东高速路桥集团股份有限公司", "target": "山东高速投资控股有限公司", "value": 4.740367410471791e-10}, {"source": "山东高速路桥集团股份有限公司", "target": "锡林浩特鲁地矿业有限公司", "value": 1.3069870146015084e-08}, {"source": "山东高速路桥集团股份有限公司", "target": "山东高速四川产业发展有限公司", "value": 0.0}, {"source": "山东高速路桥集团股份有限公司", "target": "山东高速青岛发展有限公司", "value": 2.9627296315448698e-08}, {"source": "山东高速路桥集团股份有限公司", "target": "山东高速物资集团总公司", "value": 1.3918209683769837e-06}, {"source": "山东高速路桥集团股份有限公司", "target": "山东高速交通物流投资有限公司", "value": 1.2741303429876755e-07}, {"source": "山东高速路桥集团股份有限公司", "target": "山东利津黄河公路大桥有限公司", "value": 8.062010574523811e-09}, {"source": "山东高速路桥集团股份有限公司", "target": "云南锁蒙高速公路有限公司", "value": 1.005426002301804e-06}, {"source": "山东高速路桥集团股份有限公司", "target": "山东高速物资储运有限公司", "value": 1.1188663804111158e-07}, {"source": "山东高速路桥集团股份有限公司", "target": "莱州市北莱公路投资有限公司", "value": 4.0573312562736326e-08}, {"source": "山东高速路桥集团股份有限公司", "target": "山东省高速公路建设材料有限公司", "value": 1.9752078276535815e-06}, {"source": "山东高速路桥集团股份有限公司", "target": "内蒙古鲁桥置业有限公司", "value": 7.323867649178917e-09}, {"source": "山东高速路桥集团股份有限公司", "target": "山东农村经济开发投资公司", "value": 1.567918845722567e-08}, {"source": "山东高速路桥集团股份有限公司", "target": "高速集团四川乐自公路有限公司", "value": 9.582356447305571e-07}, {"source": "山东高速路桥集团股份有限公司", "target": "山东高速齐鲁建设集团公司", "value": 1.4734077704762858e-08}, {"source": "山东高速路桥集团股份有限公司", "target": "山东高速青岛胶州湾大桥投资发展有限公司", "value": 2.1089979258607046e-08}, {"source": "山东高速路桥集团股份有限公司", "target": "山东高速青岛公路有限公司", "value": 2.1137213633875676e-07}, {"source": "山东高速路桥集团股份有限公司", "target": "湖南衡邵高速公路有限公司", "value": 7.699330142913696e-08}, {"source": "山东高速路桥集团股份有限公司", "target": "山东高速云南发展有限公司", "value": 1.383755571825738e-07}, {"source": "山东高速路桥集团股份有限公司", "target": "山东高速工程检测有限公司", "value": 3.327145376224889e-09}, {"source": "山东高速路桥集团股份有限公司", "target": "山东高速红河交通投资有限公司", "value": 1.5170445454780396e-08}, {"source": "山东高速路桥集团股份有限公司", "target": "鲁南高速铁路有限公司", "value": 8.58566033948666e-07}, {"source": "山东高速路桥集团股份有限公司", "target": "昆明新机场高速公路建设发展有限公司", "value": 2.503675837491503e-08}, {"source": "山东高速路桥集团股份有限公司", "target": "山东高速高广公路有限公司", "value": 1.594341738317955e-06}, {"source": "山东高速路桥集团股份有限公司", "target": "山东葛洲坝济泰高速公路有限公司", "value": 1.3014619470857673e-06}, {"source": "山东高速路桥集团股份有限公司", "target": "山东葛洲坝巨单高速公路有限公司", "value": 7.338088751410333e-07}, {"source": "山东高速路桥集团股份有限公司", "target": "湖北武荆高速公路发展有限公司", "value": 3.8580707586686317e-07}, {"source": "山东高速路桥集团股份有限公司", "target": "山东高速公路发展有限公司", "value": 9.294252152992345e-08}, {"source": "山东高速路桥集团股份有限公司", "target": "宝兴国晟矿业有限公司", "value": 9.252181392224407e-10}, {"source": "山东高速路桥集团股份有限公司", "target": "山东高速湖北发展有限公司", "value": 0.0}, {"source": "山东高速路桥集团股份有限公司", "target": "山东鄄菏高速公路有限公司", "value": 2.654013203937894e-08}, {"source": "山东高速路桥集团股份有限公司", "target": "山东高速齐鲁建设集团建筑工程有限公司", "value": 3.7489957510478563e-08}, {"source": "山东高速路桥集团股份有限公司", "target": "山东高速路用新材料技术有限公司", "value": 5.9445053821496705e-08}, {"source": "山东高速路桥集团股份有限公司", "target": "山东大莱龙铁路有限责任公司", "value": 2.4886928904976904e-09}, {"source": "山东高速路桥集团股份有限公司", "target": "德州国力化工科技有限公司", "value": 1.78271674400957e-09}, {"source": "山东高速路桥集团股份有限公司", "target": "山东高速泰东公路有限公司", "value": 5.806343141500568e-06}, {"source": "山东高速路桥集团股份有限公司", "target": "山东高速青岛物流发展有限公司", "value": 2.2627974535051008e-07}, {"source": "山东高速路桥集团股份有限公司", "target": "山东高速临枣至枣木公路有限公司", "value": 1.2664793053377562e-06}, {"source": "山东高速路桥集团股份有限公司", "target": "山东高速龙青公路有限公司", "value": 4.976292957008431e-06}, {"source": "山东高速路桥集团股份有限公司", "target": "山东高速济泰城际公路有限公司", "value": 1.6205707837460217e-08}, {"source": "山东高速路桥集团股份有限公司", "target": "山东高速海南发展有限公司", "value": 6.148425830218002e-08}, {"source": "山东高速路桥集团股份有限公司", "target": "山东高速潍日公路有限公司", "value": 4.077645423615866e-06}, {"source": "山东高速路桥集团股份有限公司", "target": "山东鸿林工程技术有限公司", "value": 2.1594066543059894e-09}, {"source": "山东高速路桥集团股份有限公司", "target": "山东高速蓬莱发展有限公司", "value": 3.1939664468160446e-07}, {"source": "山东高速路桥集团股份有限公司", "target": "山东高速绿城置业投资有限公司", "value": 1.7804312097223787e-08}, {"source": "山东高速路桥集团股份有限公司", "target": "山东葛洲坝枣菏高速公路有限公司", "value": 2.4830560857501314e-06}, {"source": "山东高速路桥集团股份有限公司", "target": "青岛众钧泰置业有限公司", "value": 6.983576988641478e-09}, {"source": "山东高速路桥集团股份有限公司", "target": "山东省三益工程建设监理有限公司", "value": 3.3859767217655657e-12}, {"source": "山东高速路桥集团股份有限公司", "target": "山东高速赛邦能源科技有限公司", "value": 5.8408098450456e-11}, {"source": "山东高速路桥集团股份有限公司", "target": "山东高速国际旅游有限公司", "value": 4.949874720131036e-09}, {"source": "山东高速路桥集团股份有限公司", "target": "山东高速四川投资开发有限公司", "value": 6.071225560961747e-08}, {"source": "山东高速路桥集团股份有限公司", "target": "滕州新奥能源物流港有限公司", "value": 1.8487983122057275e-07}, {"source": "山东高速路桥集团股份有限公司", "target": "山东铁路发展基金有限公司,山东铁路投资控股集团有限公司", "value": 0.0}, {"source": "山东高速路桥集团股份有限公司", "target": "济宁市鸿翔公路勘察设计研究院有限公司", "value": 8.193217172492227e-09}, {"source": "山东高速路桥集团股份有限公司", "target": "青岛众昌泰置业有限公司", "value": 7.83007116908287e-09}, {"source": "山东高速路桥集团股份有限公司", "target": "山东高速章丘置业发展有限公司", "value": 2.0954963436826642e-09}, {"source": "山东高速路桥集团股份有限公司", "target": "山东高速集团有限公司及其下属子公司", "value": 2.6372526191651548e-05}, {"source": "山东高速路桥集团股份有限公司", "target": "山东高速集团有限公司,山东高速股份集团有限公司,青岛冠中生态股份有限公司,光合新兴产业控股集团股份有限公司", "value": 8.464941804413914e-08}]}