{
"nodes":
[{"name": "中山公用事业集团股份有限公司", "value": 17143024200.0, "category": 842}, {"name": "广发证券股份有限公司", "value": 500.0, "category": 842}, {"name": "嘉实基金管理有限公司", "value": 71.7182, "category": 842}, {"name": "易方达基金管理有限公司", "value": 3070.9354, "category": 842}, {"name": "吉林敖东药业集团股份有限公司及其控股子公司", "value": 0.1976, "category": 842}, {"name": "康美药业股份有限公司", "value": 0, "category": 842}],
"links":
[{"source": "中山公用事业集团股份有限公司", "target": "广发证券股份有限公司", "value": 2.9166382440269787e-08}, {"source": "广发证券股份有限公司", "target": "嘉实基金管理有限公司", "value": 4.183520898255513e-09}, {"source": "广发证券股份有限公司", "target": "易方达基金管理有限公司", "value": 1.7913615265152574e-07}, {"source": "广发证券股份有限公司", "target": "吉林敖东药业集团股份有限公司及其控股子公司", "value": 1.152655434039462e-11}, {"source": "广发证券股份有限公司", "target": "康美药业股份有限公司", "value": 0.0}]}