{
"nodes":
[{"name": "湖北台基半导体股份有限公司", "value": 1050374938.07, "category": 1183}, {"name": "汉江投资控股有限公司", "value": 15000.0, "category": 1183}, {"name": "北京屹唐同舟股权投资中心(有限合伙)", "value": 0, "category": 1183}, {"name": "北京屹唐同舟股权投资中心(有限合伙),汉江投资控股有限公司,王鑫,邢雁", "value": 70000.0, "category": 1183}, {"name": "恒远鑫达科技集团有限公司", "value": 10000.0, "category": 1183}, {"name": "恒远鑫达科技集团有限公司,福鼎市天悦华盈股权投资合伙企业(有限合伙)", "value": 10000.0, "category": 1183}, {"name": "恒远鑫达科技集团有限公司,深圳海德复兴资本管理有限公司", "value": 0, "category": 1183}, {"name": "深圳海德复兴资本管理有限公司,北京亦庄国际投资发展有限公司", "value": 0, "category": 1183}],
"links":
[{"source": "湖北台基半导体股份有限公司", "target": "汉江投资控股有限公司", "value": 1.4280614908388414e-05}, {"source": "湖北台基半导体股份有限公司", "target": "北京屹唐同舟股权投资中心(有限合伙)", "value": 0.0}, {"source": "湖北台基半导体股份有限公司", "target": "北京屹唐同舟股权投资中心(有限合伙),汉江投资控股有限公司,王鑫,邢雁", "value": 6.664286957247927e-05}, {"source": "湖北台基半导体股份有限公司", "target": "恒远鑫达科技集团有限公司", "value": 9.52040993892561e-06}, {"source": "湖北台基半导体股份有限公司", "target": "恒远鑫达科技集团有限公司,福鼎市天悦华盈股权投资合伙企业(有限合伙)", "value": 9.52040993892561e-06}, {"source": "湖北台基半导体股份有限公司", "target": "恒远鑫达科技集团有限公司,深圳海德复兴资本管理有限公司", "value": 0.0}, {"source": "湖北台基半导体股份有限公司", "target": "深圳海德复兴资本管理有限公司,北京亦庄国际投资发展有限公司", "value": 0.0}]}