{
"nodes":
[{"name": "深圳市银之杰科技股份有限公司", "value": 2172538834.28, "category": 792}, {"name": "深圳票联金融服务有限公司", "value": 0.4008, "category": 792}, {"name": "北京华道征信有限公司", "value": 2198.249, "category": 792}, {"name": "国誉创富国际金融服务(深圳)有限公司", "value": 0.111, "category": 792}, {"name": "易安财产保险股份有限公司", "value": 182.2992, "category": 792}, {"name": "东亚前海证券有限责任公司", "value": 2.8707, "category": 792}, {"name": "百可录(北京)科技有限公司", "value": 6.9816, "category": 792}],
"links":
[{"source": "深圳市银之杰科技股份有限公司", "target": "深圳票联金融服务有限公司", "value": 1.8448461941202947e-10}, {"source": "深圳市银之杰科技股份有限公司", "target": "北京华道征信有限公司", "value": 1.0118341570306246e-06}, {"source": "深圳市银之杰科技股份有限公司", "target": "国誉创富国际金融服务(深圳)有限公司", "value": 5.109229729225367e-11}, {"source": "深圳市银之杰科技股份有限公司", "target": "易安财产保险股份有限公司", "value": 8.391067497783794e-08}, {"source": "深圳市银之杰科技股份有限公司", "target": "东亚前海证券有限责任公司", "value": 1.3213572778096631e-09}, {"source": "深圳市银之杰科技股份有限公司", "target": "百可录(北京)科技有限公司", "value": 3.213567412392777e-09}]}