{
"nodes":
[{"name": "南京聚隆科技股份有限公司", "value": 985393425.43, "category": 864}, {"name": "刘越,刘曙阳", "value": 0, "category": 864}, {"name": "南京卫岗乳业有限公司", "value": 56.66, "category": 864}, {"name": "泰州卫岗乳品有限公司", "value": 4.22, "category": 864}, {"name": "徐州卫岗乳品有限公司", "value": 5.09, "category": 864}],
"links":
[{"source": "南京聚隆科技股份有限公司", "target": "刘越,刘曙阳", "value": 0.0}, {"source": "南京聚隆科技股份有限公司", "target": "南京卫岗乳业有限公司", "value": 5.7499876229918066e-08}, {"source": "南京聚隆科技股份有限公司", "target": "泰州卫岗乳品有限公司", "value": 4.282553436114618e-09}, {"source": "南京聚隆科技股份有限公司", "target": "徐州卫岗乳品有限公司", "value": 5.165449523654836e-09}]}