{
"nodes":
[{"name": "福建东方银星投资股份有限公司", "value": 370495100.0, "category": 609}, {"name": "上海城开集团龙城置业有限公司", "value": 92.0, "category": 609}, {"name": "徐州伟天化工有限公司", "value": 12789.0, "category": 609}, {"name": "中庚汇建设发展有限公司", "value": 7494.0, "category": 609}, {"name": "徐州伟天化工有限公司,徐州腾达焦化有限公司", "value": 14965.32, "category": 609}],
"links":
[{"source": "福建东方银星投资股份有限公司", "target": "上海城开集团龙城置业有限公司", "value": 3.9307789821247824e-07}, {"source": "福建东方银星投资股份有限公司", "target": "徐州伟天化工有限公司", "value": 5.4642100437384615e-05}, {"source": "福建东方银星投资股份有限公司", "target": "中庚汇建设发展有限公司", "value": 3.2018758360916433e-05}, {"source": "福建东方银星投资股份有限公司", "target": "徐州伟天化工有限公司,徐州腾达焦化有限公司", "value": 6.394061447475179e-05}]}