{"node": [{"name": "海南亚太实业发展股份有限公司", "value": 1, "category": 1080}, {"name": "北京大市投资有限公司", "value": 7703095503.63, "category": 1080}, {"name": "兰州亚太工贸集团有限公司", "value": 7703095503.63, "category": 1080}, {"name": "兰州太华投资控股有限公司", "value": 7703095503.63, "category": 1080}, {"name": "芜湖长元股权投资基金(有限合伙)", "value": 7703095503.63, "category": 1080}], "link": [{"source": "海南亚太实业发展股份有限公司", "target": "北京大市投资有限公司", "value": 9.97}, {"source": "海南亚太实业发展股份有限公司", "target": "兰州亚太工贸集团有限公司", "value": 9.95}, {"source": "海南亚太实业发展股份有限公司", "target": "兰州太华投资控股有限公司", "value": 6.98}, {"source": "海南亚太实业发展股份有限公司", "target": "芜湖长元股权投资基金(有限合伙)", "value": 2.17}]}