{"nodes": [{"name": "安徽安凯汽车股份有限公司", "value": 1, "category": 1080}, {"name": "安徽江淮汽车集团股份有限公司", "value": 13828120461.42, "category": 1080}, {"name": "安徽江淮汽车集团股份有限公司", "value": 13828120461.42, "category": 1080}, {"name": "安徽省投资集团控股有限公司", "value": 13828120461.42, "category": 1080}, {"name": "欧阳小侠", "value": 13828120461.42, "category": 1080}], "links": [{"source": "安徽安凯汽车股份有限公司", "target": "安徽江淮汽车集团股份有限公司", "value": 25.2}, {"source": "安徽安凯汽车股份有限公司", "target": "安徽江淮汽车集团股份有限公司", "value": 25.2}, {"source": "安徽安凯汽车股份有限公司", "target": "安徽省投资集团控股有限公司", "value": 16.58}, {"source": "安徽安凯汽车股份有限公司", "target": "欧阳小侠", "value": 0.67}]}