{"nodes": [{"name": "湖南华菱钢铁股份有限公司", "value": 1, "category": 1080}, {"name": "湖南华菱钢铁集团有限责任公司", "value": 890154792.18, "category": 1080}, {"name": "香港中央结算有限公司(陆股通)", "value": 890154792.18, "category": 1080}, {"name": "四川郎信投资有限责任公司", "value": 890154792.18, "category": 1080}, {"name": "中国农业银行股份有限公司", "value": 890154792.18, "category": 1080}, {"name": "中国农业银行股份有限公司", "value": 890154792.18, "category": 1080}, {"name": "中国农业银行股份有限公司", "value": 890154792.18, "category": 1080}, {"name": "华夏人寿保险股份有限公司", "value": 890154792.18, "category": 1080}, {"name": "中国银行股份有限公司", "value": 890154792.18, "category": 1080}, {"name": "中国银行股份有限公司", "value": 890154792.18, "category": 1080}, {"name": "四川峨胜水泥集团股份有限公司", "value": 890154792.18, "category": 1080}, {"name": "中国农业银行股份有限公司", "value": 890154792.18, "category": 1080}, {"name": "中国农业银行股份有限公司", "value": 890154792.18, "category": 1080}, {"name": "中国农业银行股份有限公司", "value": 890154792.18, "category": 1080}, {"name": "西藏林芝福恒珠宝金行有限公司", "value": 890154792.18, "category": 1080}], "links": [{"source": "湖南华菱钢铁股份有限公司", "target": "湖南华菱钢铁集团有限责任公司", "value": 60.98}, {"source": "湖南华菱钢铁股份有限公司", "target": "香港中央结算有限公司(陆股通)", "value": 2.01}, {"source": "湖南华菱钢铁股份有限公司", "target": "四川郎信投资有限责任公司", "value": 0.76}, {"source": "湖南华菱钢铁股份有限公司", "target": "中国农业银行股份有限公司", "value": 0.48}, {"source": "湖南华菱钢铁股份有限公司", "target": "中国农业银行股份有限公司", "value": 0.48}, {"source": "湖南华菱钢铁股份有限公司", "target": "中国农业银行股份有限公司", "value": 0.48}, {"source": "湖南华菱钢铁股份有限公司", "target": "华夏人寿保险股份有限公司", "value": 0.34}, {"source": "湖南华菱钢铁股份有限公司", "target": "中国银行股份有限公司", "value": 0.31}, {"source": "湖南华菱钢铁股份有限公司", "target": "中国银行股份有限公司", "value": 0.31}, {"source": "湖南华菱钢铁股份有限公司", "target": "四川峨胜水泥集团股份有限公司", "value": 0.31}, {"source": "湖南华菱钢铁股份有限公司", "target": "中国农业银行股份有限公司", "value": 0.27}, {"source": "湖南华菱钢铁股份有限公司", "target": "中国农业银行股份有限公司", "value": 0.27}, {"source": "湖南华菱钢铁股份有限公司", "target": "中国农业银行股份有限公司", "value": 0.27}, {"source": "湖南华菱钢铁股份有限公司", "target": "西藏林芝福恒珠宝金行有限公司", "value": 0.22}]}