{"nodes": [{"name": "上海海得控制系统股份有限公司", "value": 1, "category": 1080}, {"name": "上海证券", "value": 2750811617.63, "category": 1080}, {"name": "前海开源基金", "value": 2750811617.63, "category": 1080}, {"name": "上海证券", "value": 2750811617.63, "category": 1080}, {"name": "上海证券", "value": 2750811617.63, "category": 1080}], "links": [{"source": "上海海得控制系统股份有限公司", "target": "上海证券", "value": 4.05}, {"source": "上海海得控制系统股份有限公司", "target": "前海开源基金", "value": 1.24}, {"source": "上海海得控制系统股份有限公司", "target": "上海证券", "value": 0.75}, {"source": "上海海得控制系统股份有限公司", "target": "上海证券", "value": 0.75}]}