{"nodes": [{"name": "天水华天科技股份有限公司", "value": 1, "category": 1080}, {"name": "广州汇垠天粤股权投资基金管理有限公司", "value": 6899371068.28, "category": 1080}, {"name": "中央汇金资产管理有限责任公司", "value": 6899371068.28, "category": 1080}, {"name": "香港中央结算有限公司(陆股通)", "value": 6899371068.28, "category": 1080}, {"name": "杭州友旺电子有限公司", "value": 6899371068.28, "category": 1080}, {"name": "中国建设银行股份有限公司", "value": 6899371068.28, "category": 1080}, {"name": "中国建设银行股份有限公司", "value": 6899371068.28, "category": 1080}, {"name": "中国工商银行股份有限公司", "value": 6899371068.28, "category": 1080}, {"name": "中国工商银行股份有限公司", "value": 6899371068.28, "category": 1080}, {"name": "天水华天电子集团股份有限公司", "value": 6899371068.28, "category": 1080}, {"name": "中国农业银行股份有限公司-华安智能生活混合型证券投资基金", "value": 6899371068.28, "category": 1080}, {"name": "杭州友旺电子有限公司", "value": 6899371068.28, "category": 1080}, {"name": "香港中央结算有限公司(陆股通)", "value": 6899371068.28, "category": 1080}, {"name": "中央汇金资产管理有限责任公司", "value": 6899371068.28, "category": 1080}, {"name": "招商财富-招商银行-汇垠天粤1号专项资产管理计划", "value": 6899371068.28, "category": 1080}, {"name": "中国工商银行股份有限公司-华安媒体互联网混合型证券投资基金", "value": 6899371068.28, "category": 1080}, {"name": "天水华天电子集团股份有限公司", "value": 6899371068.28, "category": 1080}], "links": [{"source": "天水华天科技股份有限公司", "target": "广州汇垠天粤股权投资基金管理有限公司", "value": 1.41}, {"source": "天水华天科技股份有限公司", "target": "中央汇金资产管理有限责任公司", "value": 0.77}, {"source": "天水华天科技股份有限公司", "target": "香港中央结算有限公司(陆股通)", "value": 0.42}, {"source": "天水华天科技股份有限公司", "target": "杭州友旺电子有限公司", "value": 0.38}, {"source": "天水华天科技股份有限公司", "target": "中国建设银行股份有限公司", "value": 0.34}, {"source": "天水华天科技股份有限公司", "target": "中国建设银行股份有限公司", "value": 0.34}, {"source": "天水华天科技股份有限公司", "target": "中国工商银行股份有限公司", "value": 0.29}, {"source": "天水华天科技股份有限公司", "target": "中国工商银行股份有限公司", "value": 0.29}, {"source": "天水华天科技股份有限公司", "target": "天水华天电子集团股份有限公司", "value": 26.12}, {"source": "天水华天科技股份有限公司", "target": "中国农业银行股份有限公司-华安智能生活混合型证券投资基金", "value": 0.55}, {"source": "天水华天科技股份有限公司", "target": "杭州友旺电子有限公司", "value": 0.38}, {"source": "天水华天科技股份有限公司", "target": "香港中央结算有限公司(陆股通)", "value": 0.43}, {"source": "天水华天科技股份有限公司", "target": "中央汇金资产管理有限责任公司", "value": 0.77}, {"source": "天水华天科技股份有限公司", "target": "招商财富-招商银行-汇垠天粤1号专项资产管理计划", "value": 1.4}, {"source": "天水华天科技股份有限公司", "target": "中国工商银行股份有限公司-华安媒体互联网混合型证券投资基金", "value": 1.58}, {"source": "天水华天科技股份有限公司", "target": "天水华天电子集团股份有限公司", "value": 25.97}]}