{"node": [{"name": "四川川大智胜软件股份有限公司", "value": 1, "category": 1080}, {"name": "四川智胜视科航空航天技术有限公司", "value": 3438111400.0, "category": 1080}, {"name": "四川大学", "value": 3438111400.0, "category": 1080}, {"name": "成都西南民航空管实业有限公司", "value": 3438111400.0, "category": 1080}, {"name": "成都西南民航巨龙实业有限公司", "value": 3438111400.0, "category": 1080}, {"name": "中央汇金资产管理有限责任公司", "value": 3438111400.0, "category": 1080}, {"name": "四川力攀投资咨询有限责任公司", "value": 3438111400.0, "category": 1080}], "link": [{"source": "四川川大智胜软件股份有限公司", "target": "四川智胜视科航空航天技术有限公司", "value": 6.99}, {"source": "四川川大智胜软件股份有限公司", "target": "四川大学", "value": 6.97}, {"source": "四川川大智胜软件股份有限公司", "target": "成都西南民航空管实业有限公司", "value": 3.37}, {"source": "四川川大智胜软件股份有限公司", "target": "成都西南民航巨龙实业有限公司", "value": 1.96}, {"source": "四川川大智胜软件股份有限公司", "target": "中央汇金资产管理有限责任公司", "value": 1.88}, {"source": "四川川大智胜软件股份有限公司", "target": "四川力攀投资咨询有限责任公司", "value": 1.19}]}