{"node": [{"name": "深圳齐心集团股份有限公司", "value": 1, "category": 1080}, {"name": "深圳市齐心控股有限公司", "value": 12977573530.22, "category": 1080}, {"name": "万向信托有限公司", "value": 12977573530.22, "category": 1080}, {"name": "全国社保基金一零四组合", "value": 12977573530.22, "category": 1080}, {"name": "宁波梅山保税港区东芷投资合伙企业(有限合伙)", "value": 12977573530.22, "category": 1080}, {"name": "全国社保基金一零三组合", "value": 12977573530.22, "category": 1080}, {"name": "上海浦东发展银行股份有限公司", "value": 12977573530.22, "category": 1080}, {"name": "上海浦东发展银行股份有限公司", "value": 12977573530.22, "category": 1080}, {"name": "国信证券股份有限公司", "value": 12977573530.22, "category": 1080}, {"name": "国信证券股份有限公司", "value": 12977573530.22, "category": 1080}], "link": [{"source": "深圳齐心集团股份有限公司", "target": "深圳市齐心控股有限公司", "value": 43.14}, {"source": "深圳齐心集团股份有限公司", "target": "万向信托有限公司", "value": 4.81}, {"source": "深圳齐心集团股份有限公司", "target": "全国社保基金一零四组合", "value": 4.05}, {"source": "深圳齐心集团股份有限公司", "target": "宁波梅山保税港区东芷投资合伙企业(有限合伙)", "value": 2.29}, {"source": "深圳齐心集团股份有限公司", "target": "全国社保基金一零三组合", "value": 1.56}, {"source": "深圳齐心集团股份有限公司", "target": "上海浦东发展银行股份有限公司", "value": 1.01}, {"source": "深圳齐心集团股份有限公司", "target": "上海浦东发展银行股份有限公司", "value": 1.01}, {"source": "深圳齐心集团股份有限公司", "target": "国信证券股份有限公司", "value": 0.94}, {"source": "深圳齐心集团股份有限公司", "target": "国信证券股份有限公司", "value": 0.94}]}