{"nodes": [{"name": "艾格拉斯股份有限公司", "value": 1, "category": 1080}, {"name": "日照义聚股权投资中心(有限合伙)", "value": 816169132.26, "category": 1080}, {"name": "日照银杏树股权投资基金(有限合伙)", "value": 816169132.26, "category": 1080}, {"name": "新纪元期货股份有限公司", "value": 816169132.26, "category": 1080}, {"name": "北京康海天达科技有限公司", "value": 816169132.26, "category": 1080}, {"name": "宁波乐源盛世投资管理有限公司", "value": 816169132.26, "category": 1080}, {"name": "上海哲安投资管理有限公司", "value": 816169132.26, "category": 1080}, {"name": "北京骊悦金实投资中心(有限合伙)", "value": 816169132.26, "category": 1080}, {"name": "浙江巨龙控股集团有限公司", "value": 816169132.26, "category": 1080}, {"name": "金华巨龙文化产业投资有限公司", "value": 816169132.26, "category": 1080}, {"name": "金华巨龙文化产业投资有限公司", "value": 816169132.26, "category": 1080}, {"name": "日照义聚股权投资中心(有限合伙)", "value": 816169132.26, "category": 1080}, {"name": "上海哲安投资管理有限公司", "value": 816169132.26, "category": 1080}, {"name": "北京骊悦金实投资中心(有限合伙)", "value": 816169132.26, "category": 1080}, {"name": "浙江巨龙控股集团有限公司", "value": 816169132.26, "category": 1080}, {"name": "北京骊悦金实投资中心(有限合伙)", "value": 816169132.26, "category": 1080}, {"name": "金华巨龙文化产业投资有限公司", "value": 816169132.26, "category": 1080}, {"name": "浙江巨龙控股集团有限公司", "value": 816169132.26, "category": 1080}, {"name": "日照义聚股权投资中心(有限合伙)", "value": 816169132.26, "category": 1080}, {"name": "上海哲安投资管理有限公司", "value": 816169132.26, "category": 1080}], "links": [{"source": "艾格拉斯股份有限公司", "target": "日照义聚股权投资中心(有限合伙)", "value": 12.07}, {"source": "艾格拉斯股份有限公司", "target": "日照银杏树股权投资基金(有限合伙)", "value": 2.59}, {"source": "艾格拉斯股份有限公司", "target": "新纪元期货股份有限公司", "value": 2.62}, {"source": "艾格拉斯股份有限公司", "target": "北京康海天达科技有限公司", "value": 4.3}, {"source": "艾格拉斯股份有限公司", "target": "宁波乐源盛世投资管理有限公司", "value": 4.39}, {"source": "艾格拉斯股份有限公司", "target": "上海哲安投资管理有限公司", "value": 5.49}, {"source": "艾格拉斯股份有限公司", "target": "北京骊悦金实投资中心(有限合伙)", "value": 5.49}, {"source": "艾格拉斯股份有限公司", "target": "浙江巨龙控股集团有限公司", "value": 5.96}, {"source": "艾格拉斯股份有限公司", "target": "金华巨龙文化产业投资有限公司", "value": 6.41}, {"source": "艾格拉斯股份有限公司", "target": "金华巨龙文化产业投资有限公司", "value": 6.41}, {"source": "艾格拉斯股份有限公司", "target": "日照义聚股权投资中心(有限合伙)", "value": 12.07}, {"source": "艾格拉斯股份有限公司", "target": "上海哲安投资管理有限公司", "value": 5.49}, {"source": "艾格拉斯股份有限公司", "target": "北京骊悦金实投资中心(有限合伙)", "value": 5.49}, {"source": "艾格拉斯股份有限公司", "target": "浙江巨龙控股集团有限公司", "value": 5.96}, {"source": "艾格拉斯股份有限公司", "target": "北京骊悦金实投资中心(有限合伙)", "value": 5.49}, {"source": "艾格拉斯股份有限公司", "target": "金华巨龙文化产业投资有限公司", "value": 6.6}, {"source": "艾格拉斯股份有限公司", "target": "浙江巨龙控股集团有限公司", "value": 5.96}, {"source": "艾格拉斯股份有限公司", "target": "日照义聚股权投资中心(有限合伙)", "value": 12.07}, {"source": "艾格拉斯股份有限公司", "target": "上海哲安投资管理有限公司", "value": 5.49}]}