{"node": [{"name": "牧原食品股份有限公司", "value": 1, "category": 1080}, {"name": "全国社保基金一零一组合", "value": 614869285.46, "category": 1080}, {"name": "中国工商银行股份有限公司－景顺长城新兴成长混合型证券投资基金", "value": 614869285.46, "category": 1080}, {"name": "河南鸿宝集团有限公司", "value": 614869285.46, "category": 1080}, {"name": "河南鸿宝企业管理有限公司", "value": 614869285.46, "category": 1080}, {"name": "香港中央结算有限公司(陆股通)", "value": 614869285.46, "category": 1080}, {"name": "牧原实业集团有限公司", "value": 614869285.46, "category": 1080}, {"name": "牧原实业集团有限公司", "value": 614869285.46, "category": 1080}, {"name": "全国社保基金一零一组合", "value": 614869285.46, "category": 1080}, {"name": "中国工商银行股份有限公司-景顺长城新兴成长混合型证券投资基金", "value": 614869285.46, "category": 1080}, {"name": "河南鸿宝集团有限公司", "value": 614869285.46, "category": 1080}, {"name": "河南鸿宝企业管理有限公司", "value": 614869285.46, "category": 1080}, {"name": "香港中央结算有限公司(陆股通)", "value": 614869285.46, "category": 1080}, {"name": "牧原食品股份有限公司-第二期员工持股计划", "value": 614869285.46, "category": 1080}, {"name": "牧原实业集团有限公司", "value": 614869285.46, "category": 1080}], "link": [{"source": "牧原食品股份有限公司", "target": "全国社保基金一零一组合", "value": 0.76}, {"source": "牧原食品股份有限公司", "target": "中国工商银行股份有限公司－景顺长城新兴成长混合型证券投资基金", "value": 0.92}, {"source": "牧原食品股份有限公司", "target": "河南鸿宝集团有限公司", "value": 1.16}, {"source": "牧原食品股份有限公司", "target": "河南鸿宝企业管理有限公司", "value": 2.16}, {"source": "牧原食品股份有限公司", "target": "香港中央结算有限公司(陆股通)", "value": 3.11}, {"source": "牧原食品股份有限公司", "target": "牧原食品股份有限公司", "value": 3.5}, {"source": "牧原食品股份有限公司", "target": "牧原食品股份有限公司", "value": 3.5}, {"source": "牧原食品股份有限公司", "target": "牧原食品股份有限公司", "value": 3.5}, {"source": "牧原食品股份有限公司", "target": "牧原食品股份有限公司", "value": 3.5}, {"source": "牧原食品股份有限公司", "target": "牧原食品股份有限公司", "value": 3.5}, {"source": "牧原食品股份有限公司", "target": "牧原食品股份有限公司", "value": 3.5}, {"source": "牧原食品股份有限公司", "target": "牧原食品股份有限公司", "value": 3.5}, {"source": "牧原食品股份有限公司", "target": "牧原食品股份有限公司", "value": 3.5}, {"source": "牧原食品股份有限公司", "target": "牧原食品股份有限公司", "value": 3.5}, {"source": "牧原食品股份有限公司", "target": "牧原食品股份有限公司", "value": 3.5}, {"source": "牧原食品股份有限公司", "target": "牧原食品股份有限公司", "value": 3.5}, {"source": "牧原食品股份有限公司", "target": "牧原食品股份有限公司", "value": 3.5}, {"source": "牧原食品股份有限公司", "target": "牧原食品股份有限公司", "value": 3.5}, {"source": "牧原食品股份有限公司", "target": "牧原食品股份有限公司", "value": 3.5}, {"source": "牧原食品股份有限公司", "target": "牧原食品股份有限公司", "value": 3.5}, {"source": "牧原食品股份有限公司", "target": "牧原食品股份有限公司", "value": 3.5}, {"source": "牧原食品股份有限公司", "target": "牧原实业集团有限公司", "value": 17.59}, {"source": "牧原食品股份有限公司", "target": "牧原实业集团有限公司", "value": 17.59}, {"source": "牧原食品股份有限公司", "target": "全国社保基金一零一组合", "value": 0.76}, {"source": "牧原食品股份有限公司", "target": "中国工商银行股份有限公司-景顺长城新兴成长混合型证券投资基金", "value": 0.86}, {"source": "牧原食品股份有限公司", "target": "河南鸿宝集团有限公司", "value": 1.29}, {"source": "牧原食品股份有限公司", "target": "河南鸿宝企业管理有限公司", "value": 1.7}, {"source": "牧原食品股份有限公司", "target": "香港中央结算有限公司(陆股通)", "value": 2.78}, {"source": "牧原食品股份有限公司", "target": "牧原食品股份有限公司-第二期员工持股计划", "value": 3.5}, {"source": "牧原食品股份有限公司", "target": "牧原实业集团有限公司", "value": 17.7}]}