{"nodes": [{"name": "郑州银行股份有限公司", "value": 1, "category": 1080}, {"name": "香港中央结算(代理人)有限公司", "value": 1495045045.05, "category": 1080}, {"name": "郑州市财政局", "value": 1495045045.05, "category": 1080}, {"name": "豫泰国际(河南)房地产开发有限公司", "value": 1495045045.05, "category": 1080}, {"name": "河南兴业房地产开发有限公司", "value": 1495045045.05, "category": 1080}, {"name": "中原信托有限公司", "value": 1495045045.05, "category": 1080}, {"name": "河南晨东实业有限公司", "value": 1495045045.05, "category": 1080}, {"name": "郑州投资控股有限公司", "value": 1495045045.05, "category": 1080}, {"name": "河南国原贸易有限公司", "value": 1495045045.05, "category": 1080}, {"name": "百瑞信托有限责任公司", "value": 1495045045.05, "category": 1080}, {"name": "河南盛润控股集团有限公司", "value": 1495045045.05, "category": 1080}, {"name": "河南正弘置业有限公司", "value": 1495045045.05, "category": 1080}], "links": [{"source": "郑州银行股份有限公司", "target": "香港中央结算(代理人)有限公司", "value": 25.63}, {"source": "郑州银行股份有限公司", "target": "郑州市财政局", "value": 8.29}, {"source": "郑州银行股份有限公司", "target": "豫泰国际(河南)房地产开发有限公司", "value": 4.42}, {"source": "郑州银行股份有限公司", "target": "河南兴业房地产开发有限公司", "value": 4.22}, {"source": "郑州银行股份有限公司", "target": "中原信托有限公司", "value": 4.04}, {"source": "郑州银行股份有限公司", "target": "河南晨东实业有限公司", "value": 3.82}, {"source": "郑州银行股份有限公司", "target": "郑州投资控股有限公司", "value": 3.64}, {"source": "郑州银行股份有限公司", "target": "河南国原贸易有限公司", "value": 3.36}, {"source": "郑州银行股份有限公司", "target": "百瑞信托有限责任公司", "value": 1.94}, {"source": "郑州银行股份有限公司", "target": "河南盛润控股集团有限公司", "value": 1.69}, {"source": "郑州银行股份有限公司", "target": "河南正弘置业有限公司", "value": 1.69}]}