{"nodes": [{"name": "桂林西麦食品股份有限公司", "value": 1, "category": 1080}, {"name": "广西贺州世家投资有限公司", "value": 19013235487.47, "category": 1080}, {"name": "XIE LILING", "value": 19013235487.47, "category": 1080}, {"name": "JI LI", "value": 19013235487.47, "category": 1080}, {"name": "隆化县铜麦企业管理咨询中心(有限合伙)", "value": 19013235487.47, "category": 1080}, {"name": "CASSIA NUTRITION LIMITED", "value": 19013235487.47, "category": 1080}, {"name": "SEAMILD ENTERPRISES GROUP (AUST.) PTY. LTD", "value": 19013235487.47, "category": 1080}, {"name": "BLACK RIVER FOOD 2 PTE. LTD.", "value": 19013235487.47, "category": 1080}, {"name": "桂林西麦阳光投资有限公司", "value": 19013235487.47, "category": 1080}, {"name": "Seamild Enterprises Group(Aust.)Pty. Ltd", "value": 19013235487.47, "category": 1080}, {"name": "Black River Food 2 Pte. Ltd", "value": 19013235487.47, "category": 1080}, {"name": "隆化县铜麦企业管理咨询中心(有限合伙)", "value": 19013235487.47, "category": 1080}, {"name": "Cassia Nutrition Limited", "value": 19013235487.47, "category": 1080}, {"name": "广西贺州世家投资有限公司", "value": 19013235487.47, "category": 1080}, {"name": "桂林西麦阳光投资有限公司", "value": 19013235487.47, "category": 1080}, {"name": "Black River Food2Pte. Ltd", "value": 19013235487.47, "category": 1080}, {"name": "桂林西麦阳光投资有限公司", "value": 19013235487.47, "category": 1080}, {"name": "隆化县铜麦企业管理咨询中心(有限合伙)", "value": 19013235487.47, "category": 1080}, {"name": "Cassia Nutrition Limited", "value": 19013235487.47, "category": 1080}, {"name": "Seamild Enterprises Group(Aust.)Pty. Ltd", "value": 19013235487.47, "category": 1080}, {"name": "广西贺州世家投资有限公司", "value": 19013235487.47, "category": 1080}], "links": [{"source": "桂林西麦食品股份有限公司", "target": "广西贺州世家投资有限公司", "value": 12.45}, {"source": "桂林西麦食品股份有限公司", "target": "XIE LILING", "value": 2.02}, {"source": "桂林西麦食品股份有限公司", "target": "JI LI", "value": 2.02}, {"source": "桂林西麦食品股份有限公司", "target": "隆化县铜麦企业管理咨询中心(有限合伙)", "value": 2.36}, {"source": "桂林西麦食品股份有限公司", "target": "CASSIA NUTRITION LIMITED", "value": 3.56}, {"source": "桂林西麦食品股份有限公司", "target": "SEAMILD ENTERPRISES GROUP (AUST.) PTY. LTD", "value": 12.38}, {"source": "桂林西麦食品股份有限公司", "target": "BLACK RIVER FOOD 2 PTE. LTD.", "value": 14.44}, {"source": "桂林西麦食品股份有限公司", "target": "桂林西麦阳光投资有限公司", "value": 21.1}, {"source": "桂林西麦食品股份有限公司", "target": "Seamild Enterprises Group(Aust.)Pty. Ltd", "value": 12.38}, {"source": "桂林西麦食品股份有限公司", "target": "Black River Food 2 Pte. Ltd", "value": 14.44}, {"source": "桂林西麦食品股份有限公司", "target": "隆化县铜麦企业管理咨询中心(有限合伙)", "value": 2.36}, {"source": "桂林西麦食品股份有限公司", "target": "Cassia Nutrition Limited", "value": 3.56}, {"source": "桂林西麦食品股份有限公司", "target": "广西贺州世家投资有限公司", "value": 12.45}, {"source": "桂林西麦食品股份有限公司", "target": "桂林西麦阳光投资有限公司", "value": 21.1}, {"source": "桂林西麦食品股份有限公司", "target": "Black River Food2Pte. Ltd", "value": 19.248}, {"source": "桂林西麦食品股份有限公司", "target": "桂林西麦阳光投资有限公司", "value": 28.1361}, {"source": "桂林西麦食品股份有限公司", "target": "隆化县铜麦企业管理咨询中心(有限合伙)", "value": 3.1451}, {"source": "桂林西麦食品股份有限公司", "target": "Cassia Nutrition Limited", "value": 4.752}, {"source": "桂林西麦食品股份有限公司", "target": "Seamild Enterprises Group(Aust.)Pty. Ltd", "value": 16.5125}, {"source": "桂林西麦食品股份有限公司", "target": "广西贺州世家投资有限公司", "value": 16.601}]}