{"node": [{"name": "深圳市银之杰科技股份有限公司", "value": 1, "category": 1080}, {"name": "兴业国际信托有限公司", "value": 2224176983.95, "category": 1080}, {"name": "深圳弘道天瑞投资有限责任公司", "value": 2224176983.95, "category": 1080}, {"name": "深圳市明达资产管理有限公司", "value": 2224176983.95, "category": 1080}, {"name": "武汉亘星投资有限公司", "value": 2224176983.95, "category": 1080}], "link": [{"source": "深圳市银之杰科技股份有限公司", "target": "兴业国际信托有限公司", "value": 1.91}, {"source": "深圳市银之杰科技股份有限公司", "target": "深圳弘道天瑞投资有限责任公司", "value": 1.29}, {"source": "深圳市银之杰科技股份有限公司", "target": "深圳市明达资产管理有限公司", "value": 1.12}, {"source": "深圳市银之杰科技股份有限公司", "target": "武汉亘星投资有限公司", "value": 0.71}]}