{"node": [{"name": "广东溢多利生物科技股份有限公司", "value": 1, "category": 1080}, {"name": "珠海市金大地投资有限公司", "value": 679550882.06, "category": 1080}, {"name": "珠海市金大地投资有限公司", "value": 679550882.06, "category": 1080}, {"name": "正安县态生源企业管理有限公司", "value": 679550882.06, "category": 1080}, {"name": "深圳菁英时代基金管理股份有限公司", "value": 679550882.06, "category": 1080}, {"name": "珠海市金大地投资有限公司", "value": 679550882.06, "category": 1080}, {"name": "深圳菁英时代基金管理股份有限公司", "value": 679550882.06, "category": 1080}, {"name": "深圳菁英时代基金管理股份有限公司", "value": 679550882.06, "category": 1080}, {"name": "珠海市金大地投资有限公司", "value": 679550882.06, "category": 1080}], "link": [{"source": "广东溢多利生物科技股份有限公司", "target": "珠海市金大地投资有限公司", "value": 34.7241}, {"source": "广东溢多利生物科技股份有限公司", "target": "珠海市金大地投资有限公司", "value": 34.75}, {"source": "广东溢多利生物科技股份有限公司", "target": "正安县态生源企业管理有限公司", "value": 4.31}, {"source": "广东溢多利生物科技股份有限公司", "target": "广东溢多利生物科技股份有限公司", "value": 4.42}, {"source": "广东溢多利生物科技股份有限公司", "target": "广东溢多利生物科技股份有限公司", "value": 4.42}, {"source": "广东溢多利生物科技股份有限公司", "target": "广东溢多利生物科技股份有限公司", "value": 4.42}, {"source": "广东溢多利生物科技股份有限公司", "target": "广东溢多利生物科技股份有限公司", "value": 4.42}, {"source": "广东溢多利生物科技股份有限公司", "target": "广东溢多利生物科技股份有限公司", "value": 4.42}, {"source": "广东溢多利生物科技股份有限公司", "target": "广东溢多利生物科技股份有限公司", "value": 4.42}, {"source": "广东溢多利生物科技股份有限公司", "target": "广东溢多利生物科技股份有限公司", "value": 4.42}, {"source": "广东溢多利生物科技股份有限公司", "target": "广东溢多利生物科技股份有限公司", "value": 4.42}, {"source": "广东溢多利生物科技股份有限公司", "target": "广东溢多利生物科技股份有限公司", "value": 4.42}, {"source": "广东溢多利生物科技股份有限公司", "target": "广东溢多利生物科技股份有限公司", "value": 4.42}, {"source": "广东溢多利生物科技股份有限公司", "target": "深圳菁英时代基金管理股份有限公司", "value": 5.26}, {"source": "广东溢多利生物科技股份有限公司", "target": "珠海市金大地投资有限公司", "value": 34.82}, {"source": "广东溢多利生物科技股份有限公司", "target": "深圳菁英时代基金管理股份有限公司", "value": 5.26}, {"source": "广东溢多利生物科技股份有限公司", "target": "深圳菁英时代基金管理股份有限公司", "value": 5.26}, {"source": "广东溢多利生物科技股份有限公司", "target": "珠海市金大地投资有限公司", "value": 34.82}]}