{"nodes": [{"name": "广东星徽精密制造股份有限公司", "value": 1, "category": 1080}, {"name": "广东星野投资有限责任公司", "value": 1744460600.0, "category": 1080}, {"name": "广东星野投资有限责任公司", "value": 1744460600.0, "category": 1080}, {"name": "逹泰電商投資有限公司", "value": 1744460600.0, "category": 1080}, {"name": "SUNVALLEYE", "value": 1744460600.0, "category": 1080}, {"name": "遵义顺择齐心咨询服务中心(有限合伙)", "value": 1744460600.0, "category": 1080}, {"name": "深圳市泽宝财富投资管理合伙企业(有限合伙)", "value": 1744460600.0, "category": 1080}, {"name": "深圳市恒富致远投资管理合伙企业(有限合伙)", "value": 1744460600.0, "category": 1080}, {"name": "深圳市广富云网投资管理合伙企业(有限合伙)", "value": 1744460600.0, "category": 1080}, {"name": "深圳市亿网众盈投资管理合伙企业(有限合伙)", "value": 1744460600.0, "category": 1080}], "links": [{"source": "广东星徽精密制造股份有限公司", "target": "广东星野投资有限责任公司", "value": 31.55}, {"source": "广东星徽精密制造股份有限公司", "target": "广东星野投资有限责任公司", "value": 32.41}, {"source": "广东星徽精密制造股份有限公司", "target": "逹泰電商投資有限公司", "value": 3.54}, {"source": "广东星徽精密制造股份有限公司", "target": "SUNVALLEYE", "value": 3.13}, {"source": "广东星徽精密制造股份有限公司", "target": "遵义顺择齐心咨询服务中心(有限合伙)", "value": 1.49}, {"source": "广东星徽精密制造股份有限公司", "target": "深圳市泽宝财富投资管理合伙企业(有限合伙)", "value": 1.18}, {"source": "广东星徽精密制造股份有限公司", "target": "深圳市恒富致远投资管理合伙企业(有限合伙)", "value": 1.18}, {"source": "广东星徽精密制造股份有限公司", "target": "深圳市广富云网投资管理合伙企业(有限合伙)", "value": 1.18}, {"source": "广东星徽精密制造股份有限公司", "target": "深圳市亿网众盈投资管理合伙企业(有限合伙)", "value": 1.18}]}