{"nodes": [{"name": "上海雪榕生物科技股份有限公司", "value": 1, "category": 1080}, {"name": "深圳市云图资产管理服务有限公司", "value": 1743965286.55, "category": 1080}, {"name": "华泰证券股份有限公司", "value": 1743965286.55, "category": 1080}, {"name": "华泰证券股份有限公司", "value": 1743965286.55, "category": 1080}, {"name": "德州均益投资合伙企业(有限合伙)", "value": 1743965286.55, "category": 1080}, {"name": "广发证券股份有限公司", "value": 1743965286.55, "category": 1080}, {"name": "广发证券股份有限公司", "value": 1743965286.55, "category": 1080}, {"name": "广发银行股份有限公司", "value": 1743965286.55, "category": 1080}, {"name": "深圳市云图资产管理服务有限公司", "value": 1743965286.55, "category": 1080}], "links": [{"source": "上海雪榕生物科技股份有限公司", "target": "深圳市云图资产管理服务有限公司", "value": 8.85}, {"source": "上海雪榕生物科技股份有限公司", "target": "华泰证券股份有限公司", "value": 1.4}, {"source": "上海雪榕生物科技股份有限公司", "target": "华泰证券股份有限公司", "value": 1.4}, {"source": "上海雪榕生物科技股份有限公司", "target": "德州均益投资合伙企业(有限合伙)", "value": 1.28}, {"source": "上海雪榕生物科技股份有限公司", "target": "广发证券股份有限公司", "value": 0.59}, {"source": "上海雪榕生物科技股份有限公司", "target": "广发证券股份有限公司", "value": 0.59}, {"source": "上海雪榕生物科技股份有限公司", "target": "广发银行股份有限公司", "value": 0.54}, {"source": "上海雪榕生物科技股份有限公司", "target": "深圳市云图资产管理服务有限公司", "value": 8.85}]}