{"nodes": [{"name": "江西新余国科科技股份有限公司", "value": 1, "category": 1080}, {"name": "江西省军工控股集团有限公司", "value": 1408578970.32, "category": 1080}, {"name": "江西钢丝厂有限责任公司", "value": 1408578970.32, "category": 1080}, {"name": "新余科信投资管理中心(有限合伙)", "value": 1408578970.32, "category": 1080}, {"name": "全国社会保障基金理事会转持一户", "value": 1408578970.32, "category": 1080}, {"name": "新余国晖投资管理中心(有限合伙)", "value": 1408578970.32, "category": 1080}, {"name": "中国建设银行股份有限公司", "value": 1408578970.32, "category": 1080}, {"name": "中国建设银行股份有限公司", "value": 1408578970.32, "category": 1080}, {"name": "中国建设银行股份有限公司", "value": 1408578970.32, "category": 1080}, {"name": "中国建设银行股份有限公司", "value": 1408578970.32, "category": 1080}, {"name": "中国建设银行股份有限公司", "value": 1408578970.32, "category": 1080}, {"name": "中国建设银行股份有限公司", "value": 1408578970.32, "category": 1080}], "links": [{"source": "江西新余国科科技股份有限公司", "target": "江西省军工控股集团有限公司", "value": 36.83}, {"source": "江西新余国科科技股份有限公司", "target": "江西钢丝厂有限责任公司", "value": 28.17}, {"source": "江西新余国科科技股份有限公司", "target": "新余科信投资管理中心(有限合伙)", "value": 5.18}, {"source": "江西新余国科科技股份有限公司", "target": "全国社会保障基金理事会转持一户", "value": 2.5}, {"source": "江西新余国科科技股份有限公司", "target": "新余国晖投资管理中心(有限合伙)", "value": 2.33}, {"source": "江西新余国科科技股份有限公司", "target": "中国建设银行股份有限公司", "value": 0.65}, {"source": "江西新余国科科技股份有限公司", "target": "中国建设银行股份有限公司", "value": 0.65}, {"source": "江西新余国科科技股份有限公司", "target": "中国建设银行股份有限公司", "value": 0.65}, {"source": "江西新余国科科技股份有限公司", "target": "中国建设银行股份有限公司", "value": 0.23}, {"source": "江西新余国科科技股份有限公司", "target": "中国建设银行股份有限公司", "value": 0.23}, {"source": "江西新余国科科技股份有限公司", "target": "中国建设银行股份有限公司", "value": 0.23}]}