{
"nodes":
[{"name": "深圳市捷顺科技实业股份有限公司\n002609.SZ", "value": 2578408650.5, "itemStyle": {"color": "red"}, "category": 0}, {"name": "南京墨博云舟信息科技有限公司", "value": 0.0, "itemStyle": {"color": "blue", "borderType": "dotted"}, "category": 1}, {"name": "中装捷顺智慧交通(江苏)有限公司", "value": 3.13, "itemStyle": {"color": "blue", "borderType": "dotted"}, "category": 1}, {"name": "石家庄捷顺智慧科技有限公司", "value": 19.2, "itemStyle": {"color": "blue", "borderType": "dotted"}, "category": 1}, {"name": "福州捷顺智慧电子科技有限公司", "value": 6.99, "itemStyle": {"color": "blue", "borderType": "dotted"}, "category": 1}, {"name": "长沙捷顺智慧电子科技有限公司", "value": 90.29, "itemStyle": {"color": "blue", "borderType": "dotted"}, "category": 1}, {"name": "贵阳捷顺科技有限公司", "value": 139.81, "itemStyle": {"color": "blue", "borderType": "dotted"}, "category": 1}, {"name": "青岛捷顺信息科技有限公司", "value": 72.58, "itemStyle": {"color": "blue", "borderType": "dotted"}, "category": 1}, {"name": "郑州捷顺科技有限公司", "value": 106.72, "itemStyle": {"color": "blue", "borderType": "dotted"}, "category": 1}, {"name": "广东捷顺信宏智慧交通发展有限公司", "value": 0.0, "itemStyle": {"color": "blue", "borderType": "dotted"}, "category": 1}],
"links":
[{"source": "深圳市捷顺科技实业股份有限公司", "target": "南京墨博云舟信息科技有限公司", "value": 0.0}, {"source": "深圳市捷顺科技实业股份有限公司", "target": "中装捷顺智慧交通(江苏)有限公司", "value": 1.1038577997361795e-09}, {"source": "深圳市捷顺科技实业股份有限公司", "target": "石家庄捷顺智慧科技有限公司", "value": 6.771268292311389e-09}, {"source": "深圳市捷顺科技实业股份有限公司", "target": "福州捷顺智慧电子科技有限公司", "value": 2.465164862669615e-09}, {"source": "深圳市捷顺科技实业股份有限公司", "target": "长沙捷顺智慧电子科技有限公司", "value": 3.1842594485041425e-08}, {"source": "深圳市捷顺科技实业股份有限公司", "target": "贵阳捷顺科技有限公司", "value": 4.930682395562788e-08}, {"source": "深圳市捷顺科技实业股份有限公司", "target": "青岛捷顺信息科技有限公司", "value": 2.559680482583128e-08}, {"source": "深圳市捷顺科技实业股份有限公司", "target": "郑州捷顺科技有限公司", "value": 3.763696625809747e-08}, {"source": "深圳市捷顺科技实业股份有限公司", "target": "广东捷顺信宏智慧交通发展有限公司", "value": 0.0}]}