{
"nodes":
[{"name": "北京易华录信息技术股份有限公司\n300212.SZ", "value": 11956042000.0, "itemStyle": {"color": "red"}, "category": 0}, {"name": "中国华录集团有限公司", "value": 671.58, "itemStyle": {"color": "blue", "borderType": "dotted"}, "category": 1}, {"name": "中国华录·松下电子信息有限公司", "value": 30230.38, "itemStyle": {"color": "blue", "borderType": "dotted"}, "category": 1}, {"name": "蓝安数据信息技术有限公司", "value": 11399.15, "itemStyle": {"color": "blue", "borderType": "dotted"}, "category": 1}, {"name": "泰州易华录数据湖信息技术有限公司", "value": 44731.51, "itemStyle": {"color": "blue", "borderType": "dotted"}, "category": 1}, {"name": "华录资本控股有限公司", "value": 1104.902, "itemStyle": {"color": "blue", "borderType": "dotted"}, "category": 1}, {"name": "延边鸿运投资有限公司,吉林省弘锦建设工程有限公司,华录文化产业有限公司", "value": 4447.04, "itemStyle": {"color": "blue", "borderType": "dotted"}, "category": 1}],
"links":
[{"source": "北京易华录信息技术股份有限公司", "target": "中国华录集团有限公司", "value": 5.617076286617261e-08}, {"source": "北京易华录信息技术股份有限公司", "target": "中国华录·松下电子信息有限公司", "value": 2.52846050557534e-06}, {"source": "北京易华录信息技术股份有限公司", "target": "蓝安数据信息技术有限公司", "value": 9.534217092914193e-07}, {"source": "北京易华录信息技术股份有限公司", "target": "泰州易华录数据湖信息技术有限公司", "value": 3.7413309521662773e-06}, {"source": "北京易华录信息技术股份有限公司", "target": "华录资本控股有限公司", "value": 9.241369342797558e-08}, {"source": "北京易华录信息技术股份有限公司", "target": "延边鸿运投资有限公司,吉林省弘锦建设工程有限公司,华录文化产业有限公司", "value": 3.719491784990384e-07}]}