{
"nodes":
[{"name": "深圳科创新源新材料股份有限公司\n300731.SZ", "value": 577785860.89, "itemStyle": {"color": "red"}, "category": 0}, {"name": "深圳汇智新源创业投资企业(有限合伙)", "value": 10335.0, "itemStyle": {"color": "blue", "borderType": "dotted"}, "category": 1}, {"name": "深圳嘉树控股有限公司", "value": 7000.0, "itemStyle": {"color": "blue", "borderType": "dotted"}, "category": 1}, {"name": "无锡昆成新材料科技有限公司", "value": 66.18, "itemStyle": {"color": "blue", "borderType": "dotted"}, "category": 1}, {"name": "深圳市汇智天玑股权投资企业(有限合伙),深圳市美芝资产管理有限公司", "value": 4900.0, "itemStyle": {"color": "blue", "borderType": "dotted"}, "category": 1}, {"name": "深圳市汇智天玑股权投资企业(有限合伙),深圳市汇智天玑股权投资企业(有限合伙)", "value": 4900.0, "itemStyle": {"color": "blue", "borderType": "dotted"}, "category": 1}],
"links":
[{"source": "深圳科创新源新材料股份有限公司", "target": "深圳汇智新源创业投资企业(有限合伙)", "value": 1.7887249757341497e-05}, {"source": "深圳科创新源新材料股份有限公司", "target": "深圳嘉树控股有限公司", "value": 1.2115215123501739e-05}, {"source": "深圳科创新源新材料股份有限公司", "target": "无锡昆成新材料科技有限公司", "value": 1.1454070526762074e-07}, {"source": "深圳科创新源新材料股份有限公司", "target": "深圳市汇智天玑股权投资企业(有限合伙),深圳市美芝资产管理有限公司", "value": 8.480650586451218e-06}, {"source": "深圳科创新源新材料股份有限公司", "target": "深圳市汇智天玑股权投资企业(有限合伙),深圳市汇智天玑股权投资企业(有限合伙)", "value": 8.480650586451218e-06}]}