{
"nodes":
[{"name": "重庆川仪自动化股份有限公司\n603100.SH", "value": 5060990000.0, "itemStyle": {"color": "red"}, "category": 0}, {"name": "重庆川仪精密机械有限公司", "value": 0.13, "itemStyle": {"color": "blue", "borderType": "dotted"}, "category": 1}, {"name": "重庆横河川仪有限公司", "value": 2002.05, "itemStyle": {"color": "blue", "borderType": "dotted"}, "category": 1}, {"name": "河南中平川仪电气有限公司", "value": 786.28, "itemStyle": {"color": "blue", "borderType": "dotted"}, "category": 1}, {"name": "重庆川仪微电路有限责任公司", "value": 38.63, "itemStyle": {"color": "blue", "borderType": "dotted"}, "category": 1}, {"name": "重庆四联光电科技有限公司", "value": 156.31, "itemStyle": {"color": "blue", "borderType": "dotted"}, "category": 1}, {"name": "重庆四联微电子有限公司", "value": 10.02, "itemStyle": {"color": "blue", "borderType": "dotted"}, "category": 1}, {"name": "重庆四联特种装备材料有限公司", "value": 14.73, "itemStyle": {"color": "blue", "borderType": "dotted"}, "category": 1}, {"name": "重庆安美科技有限公司", "value": 2.12, "itemStyle": {"color": "blue", "borderType": "dotted"}, "category": 1}, {"name": "重庆荣凯川仪仪表有限公司", "value": 20.1, "itemStyle": {"color": "blue", "borderType": "dotted"}, "category": 1}, {"name": "中国四联仪器仪表集团有限公司", "value": 115.77, "itemStyle": {"color": "blue", "borderType": "dotted"}, "category": 1}, {"name": "重庆耐德工业股份有限公司", "value": 0.33, "itemStyle": {"color": "blue", "borderType": "dotted"}, "category": 1}, {"name": "新中天环保股份有限公司", "value": 109.06, "itemStyle": {"color": "blue", "borderType": "dotted"}, "category": 1}, {"name": "重庆四联投资管理有限公司", "value": 11.4, "itemStyle": {"color": "blue", "borderType": "dotted"}, "category": 1}, {"name": "重庆昆仑仪表有限公司", "value": 43.1, "itemStyle": {"color": "blue", "borderType": "dotted"}, "category": 1}, {"name": "重庆优侍养老产业有限公司", "value": 23.23, "itemStyle": {"color": "blue", "borderType": "dotted"}, "category": 1}, {"name": "重庆四联光电半导体材料有限公司", "value": 9.47, "itemStyle": {"color": "blue", "borderType": "dotted"}, "category": 1}, {"name": "重庆四联新能源有限公司", "value": 78.3, "itemStyle": {"color": "blue", "borderType": "dotted"}, "category": 1}, {"name": "四联新能源江苏有限公司", "value": 22.12, "itemStyle": {"color": "blue", "borderType": "dotted"}, "category": 1}, {"name": "兰州四联光电科技有限公司", "value": 195.8, "itemStyle": {"color": "blue", "borderType": "dotted"}, "category": 1}, {"name": "重庆四联爱普建设工程有限公司", "value": 17.38, "itemStyle": {"color": "blue", "borderType": "dotted"}, "category": 1}, {"name": "巫溪县兼善光伏发电有限公司", "value": 1318.78, "itemStyle": {"color": "blue", "borderType": "dotted"}, "category": 1}, {"name": "重庆银行股份有限公司", "value": 419.65, "itemStyle": {"color": "blue", "borderType": "dotted"}, "category": 1}, {"name": "重庆四联元润科技有限公司", "value": 5.43, "itemStyle": {"color": "blue", "borderType": "dotted"}, "category": 1}, {"name": "重庆市两江新区信联产融小额贷款有限公司", "value": 8.48, "itemStyle": {"color": "blue", "borderType": "dotted"}, "category": 1}, {"name": "重庆长辉节能减排工程技术有限公司", "value": 6.36, "itemStyle": {"color": "blue", "borderType": "dotted"}, "category": 1}, {"name": "加拿大四联蓝宝石有限公司", "value": 95.1, "itemStyle": {"color": "blue", "borderType": "dotted"}, "category": 1}, {"name": "重庆四联市政工程有限公司", "value": 1.44, "itemStyle": {"color": "blue", "borderType": "dotted"}, "category": 1}, {"name": "中国四联仪器仪表集团有限公司及其子公司", "value": 5456.35, "itemStyle": {"color": "blue", "borderType": "dotted"}, "category": 1}, {"name": "重庆四联投资管理有限公司及相关子公司", "value": 10.6, "itemStyle": {"color": "blue", "borderType": "dotted"}, "category": 1}],
"links":
[{"source": "重庆川仪自动化股份有限公司", "target": "重庆川仪精密机械有限公司", "value": 2.5768597990049357e-11}, {"source": "重庆川仪自动化股份有限公司", "target": "重庆横河川仪有限公司", "value": 3.96846320045987e-07}, {"source": "重庆川仪自动化股份有限公司", "target": "河南中平川仪电气有限公司", "value": 1.5585640944320005e-07}, {"source": "重庆川仪自动化股份有限公司", "target": "重庆川仪微电路有限责任公司", "value": 7.657238002735437e-09}, {"source": "重庆川仪自动化股份有限公司", "target": "重庆四联光电科技有限公司", "value": 3.098376578326627e-08}, {"source": "重庆川仪自动化股份有限公司", "target": "重庆四联微电子有限公司", "value": 1.9861642450791888e-09}, {"source": "重庆川仪自动化股份有限公司", "target": "重庆四联特种装备材料有限公司", "value": 2.919780372257131e-09}, {"source": "重庆川仪自动化股份有限公司", "target": "重庆安美科技有限公司", "value": 4.202263672223434e-10}, {"source": "重庆川仪自动化股份有限公司", "target": "重庆荣凯川仪仪表有限公司", "value": 3.984221689230709e-09}, {"source": "重庆川仪自动化股份有限公司", "target": "中国四联仪器仪表集团有限公司", "value": 2.2947927610061644e-08}, {"source": "重庆川仪自动化股份有限公司", "target": "重庆耐德工业股份有限公司", "value": 6.54125948978176e-11}, {"source": "重庆川仪自动化股份有限公司", "target": "新中天环保股份有限公司", "value": 2.161787151380602e-08}, {"source": "重庆川仪自动化股份有限公司", "target": "重庆四联投资管理有限公司", "value": 2.2597078237427897e-09}, {"source": "重庆川仪自动化股份有限公司", "target": "重庆昆仑仪表有限公司", "value": 8.543281333624056e-09}, {"source": "重庆川仪自动化股份有限公司", "target": "重庆优侍养老产业有限公司", "value": 4.604650240837281e-09}, {"source": "重庆川仪自动化股份有限公司", "target": "重庆四联光电半导体材料有限公司", "value": 1.8771432535828263e-09}, {"source": "重庆川仪自动化股份有限公司", "target": "重庆四联新能源有限公司", "value": 1.5520624789391266e-08}, {"source": "重庆川仪自动化股份有限公司", "target": "四联新能源江苏有限公司", "value": 4.384626057999167e-09}, {"source": "重庆川仪自动化股份有限公司", "target": "兰州四联光电科技有限公司", "value": 3.881147297270511e-08}, {"source": "重庆川仪自动化股份有限公司", "target": "重庆四联爱普建设工程有限公司", "value": 3.44506333128506e-09}, {"source": "重庆川仪自动化股份有限公司", "target": "巫溪县兼善光伏发电有限公司", "value": 2.61408551210133e-07}, {"source": "重庆川仪自动化股份有限公司", "target": "重庆银行股份有限公司", "value": 8.318301651172471e-08}, {"source": "重庆川仪自动化股份有限公司", "target": "重庆四联元润科技有限公司", "value": 1.0763345160459077e-09}, {"source": "重庆川仪自动化股份有限公司", "target": "重庆市两江新区信联产融小额贷款有限公司", "value": 1.6809054688893736e-09}, {"source": "重庆川仪自动化股份有限公司", "target": "重庆长辉节能减排工程技术有限公司", "value": 1.26067910166703e-09}, {"source": "重庆川仪自动化股份有限公司", "target": "加拿大四联蓝宝石有限公司", "value": 1.8850720529643797e-08}, {"source": "重庆川仪自动化股份有限公司", "target": "重庆四联市政工程有限公司", "value": 2.854367777359313e-10}, {"source": "重庆川仪自动化股份有限公司", "target": "中国四联仪器仪表集团有限公司及其子公司", "value": 1.0815576126385063e-06}, {"source": "重庆川仪自动化股份有限公司", "target": "重庆四联投资管理有限公司及相关子公司", "value": 2.101131836111717e-09}]}